sudokugen/__init__.py
sudokugen/generator.py
sudokugen/solver.py
sudokugen/tests.py
sudokugen-0.2.1.dist-info/LICENSE
sudokugen-0.2.1.dist-info/METADATA
sudokugen-0.2.1.dist-info/WHEEL
sudokugen-0.2.1.dist-info/top_level.txt
sudokugen-0.2.1.dist-info/zip-safe
sudokugen-0.2.1.dist-info/RECORD
