Metadata-Version: 2.1
Name: sudokugen
Version: 0.2.1
Summary: A sudoku puzzle solver and generator
Home-page: http://github.com/g-k-l/sudokugen
Author: Kevin Liu
Author-email: kevin.g.k.liu@gmail.com
License: GNUPL
Platform: UNKNOWN
Requires-Python: >=3.6.9
